setup.py
src/asciiart/__init__.py
src/asciiart/commands.py
src/asciiart/parsers.py
src/asciiart/shortcuts.py
src/asciiart.egg-info/PKG-INFO
src/asciiart.egg-info/SOURCES.txt
src/asciiart.egg-info/dependency_links.txt
src/asciiart.egg-info/entry_points.txt
src/asciiart.egg-info/requires.txt
src/asciiart.egg-info/top_level.txt