Metadata-Version: 1.0
Name: asciiart
Version: 0.2
Summary: Just some ascii art stuff...
Home-page: http://asciiart.readthedocs.org/
Author: Karol Majta
Author-email: karol@karolmajta.com
License: JSON License
Keywords: asciiart
Platform: UNKNOWN
